{
  "full_name": "w3c/webcrypto",
  "html_url": "https://github.com/w3c/webcrypto",
  "start_date": "2021-06-09T13:25:38Z",
  "end_date": "2022-07-09T13:25:38Z",
  "months": 13,
  "forks_count": 63,
  "cumulative_total_committers": 25,
  "new_committers_per_month": 0,
  "total_active_committers_per_month": 1,
  "new_committers_percentage": 0,
  "commits_per_month": 2,
  "commits_per_committer_per_month": 2.00,
  "has_issues": true,
  "issues_closed_percentage": 100,
  "issues_closed_per_month": 1,
  "issues_opened_per_month": 1,
  "issues_increase_decrease": 0,
  "issues_open_age_days_stats": {
    "records": 39,
    "newest": 41,
    "percentile_25": 256,
    "median": 877,
    "mean": 953,
    "percentile_75": 1669,
    "percentile_90": 2083,
    "oldest": 2237,
    "std_dev": 755
  },
  "issues_time_to_resolve_days_stats": {
    "records": 150,
    "fastest": 0,
    "percentile_25": 1,
    "median": 39,
    "mean": 202,
    "percentile_75": 131,
    "percentile_90": 786,
    "longest": 1829,
    "std_dev": 402
  },
  "issues_open_count": 39,
  "issues_resolved_count": 150,
  "issues_resolved_to_open_ratio": 3.85,
  "issues_open_to_monthly_ratio": 39.00,
  "PRs_merged_or_closed_percentage": 100,
  "PRs_merged_vs_commits_ratio": 50,
  "PRs_merged_per_month": 1,
  "PRs_closed_per_month": 0,
  "PRs_opened_per_month": 1,
  "PRs_increase_decrease": 0,
  "PRs_open_age_days_stats": {
    "records": 1,
    "newest": 257,
    "percentile_25": 257,
    "median": 257,
    "mean": 257,
    "percentile_75": 257,
    "percentile_90": 257,
    "oldest": 257,
    "std_dev": 0
  },
  "PRs_time_to_resolve_days_stats": {
    "records": 121,
    "fastest": 0,
    "percentile_25": 0,
    "median": 11,
    "mean": 42,
    "percentile_75": 41,
    "percentile_90": 98,
    "longest": 558,
    "std_dev": 100
  },
  "PRs_open_count": 1,
  "PRs_resolved_count": 121,
  "PRs_resolved_to_open_ratio": 121.00,
  "PRs_open_to_monthly_ratio": 1.00
}
