{
  "full_name": "w3c/chinese-ig",
  "html_url": "https://github.com/w3c/chinese-ig",
  "start_date": "2021-06-09T10:57:49Z",
  "end_date": "2022-07-09T10:57:49Z",
  "months": 13,
  "forks_count": 196,
  "cumulative_total_committers": 138,
  "new_committers_per_month": 0,
  "total_active_committers_per_month": 0,
  "new_committers_percentage": 0,
  "commits_per_month": 2,
  "commits_per_committer_per_month": 2.00,
  "has_issues": true,
  "issues_closed_percentage": 0,
  "issues_closed_per_month": 0,
  "issues_opened_per_month": 0,
  "issues_increase_decrease": 0,
  "issues_open_age_days_stats": {
    "records": 5,
    "newest": 21,
    "percentile_25": 456,
    "median": 519,
    "mean": 452,
    "percentile_75": 611,
    "percentile_90": 611,
    "oldest": 654,
    "std_dev": 253
  },
  "issues_time_to_resolve_days_stats": {
    "records": 5,
    "fastest": 0,
    "percentile_25": 6,
    "median": 94,
    "mean": 114,
    "percentile_75": 122,
    "percentile_90": 122,
    "longest": 350,
    "std_dev": 142
  },
  "issues_open_count": 5,
  "issues_resolved_count": 5,
  "issues_resolved_to_open_ratio": 1.00,
  "issues_open_to_monthly_ratio": 5.00,
  "PRs_merged_or_closed_percentage": 0,
  "PRs_merged_vs_commits_ratio": 0,
  "PRs_merged_per_month": 0,
  "PRs_closed_per_month": 0,
  "PRs_opened_per_month": 0,
  "PRs_increase_decrease": 0,
  
  "PRs_time_to_resolve_days_stats": {
    "records": 233,
    "fastest": 0,
    "percentile_25": 0,
    "median": 0,
    "mean": 1,
    "percentile_75": 1,
    "percentile_90": 2,
    "longest": 49,
    "std_dev": 5
  },
  "PRs_open_count": 0,
  "PRs_resolved_count": 233,
  "PRs_resolved_to_open_ratio": 233.00,
  "PRs_open_to_monthly_ratio": 0.00
}
