{
  "full_name": "w3c/respec",
  "html_url": "https://github.com/w3c/respec",
  "start_date": "2021-06-09T11:59:55Z",
  "end_date": "2022-07-09T11:59:55Z",
  "months": 13,
  "forks_count": 403,
  "cumulative_total_committers": 120,
  "new_committers_per_month": 0,
  "total_active_committers_per_month": 3,
  "new_committers_percentage": 0,
  "commits_per_month": 24,
  "commits_per_committer_per_month": 8.00,
  "has_issues": true,
  "issues_closed_percentage": 75,
  "issues_closed_per_month": 6,
  "issues_opened_per_month": 8,
  "issues_increase_decrease": 2,
  "issues_open_age_days_stats": {
    "records": 146,
    "newest": 5,
    "percentile_25": 356,
    "median": 525,
    "mean": 679,
    "percentile_75": 936,
    "percentile_90": 1253,
    "oldest": 2307,
    "std_dev": 476
  },
  "issues_time_to_resolve_days_stats": {
    "records": 1000,
    "fastest": 0,
    "percentile_25": 0,
    "median": 10,
    "mean": 184,
    "percentile_75": 184,
    "percentile_90": 680,
    "longest": 2568,
    "std_dev": 354
  },
  "issues_open_count": 146,
  "issues_resolved_count": 1127,
  "issues_resolved_to_open_ratio": 7.72,
  "issues_open_to_monthly_ratio": 18.25,
  "PRs_merged_or_closed_percentage": 97,
  "PRs_merged_vs_commits_ratio": 70,
  "PRs_merged_per_month": 17,
  "PRs_closed_per_month": 17,
  "PRs_opened_per_month": 35,
  "PRs_increase_decrease": 0,
  "PRs_open_age_days_stats": {
    "records": 19,
    "newest": 6,
    "percentile_25": 269,
    "median": 485,
    "mean": 474,
    "percentile_75": 778,
    "percentile_90": 865,
    "oldest": 865,
    "std_dev": 268
  },
  "PRs_time_to_resolve_days_stats": {
    "records": 1000,
    "fastest": 0,
    "percentile_25": 0,
    "median": 0,
    "mean": 6,
    "percentile_75": 2,
    "percentile_90": 7,
    "longest": 695,
    "std_dev": 34
  },
  "PRs_open_count": 19,
  "PRs_resolved_count": 2882,
  "PRs_resolved_to_open_ratio": 151.68,
  "PRs_open_to_monthly_ratio": 0.54
}
